{
   "files" : {
      "file:id:a42649ab-1882-4a66-a859-ce5fd26c96aa" : {
         "desc" : "法令種別/事業のリソースです。",
         "file_name" : "18_xml.zip",
         "length" : 264077,
         "mime" : "application/octet-stream",
         "sha256" : "034e06b7773d9632c6009d2fe515f2a59e33f7129739ff8eb5e8e331fa800d1c",
         "time" : 1733652747,
         "title" : "法令種別/事業",
         "type" : "file",
         "url" : "https://laws.e-gov.go.jp/bulkdownload?file_section=2&category_cd=18&only_xml_flag=true"
      },
      "file:id:d687ce4c-6b8e-4329-88b8-257da269215c" : {
         "desc" : "XMLスキーマ情報等のリソース定義です。（e-Gov法令検索サイトが開きます）",
         "file_name" : "1",
         "length" : 800,
         "mime" : "text/html",
         "sha256" : "0b192cea4894bccd686b6ddca91e37f1100dbd7e3a3e390461e4d8c05a2aa541",
         "time" : 1733652748,
         "title" : "リソース定義",
         "type" : "file",
         "url" : "https://laws.e-gov.go.jp/help/"
      },
      "file:id:f04195c2-d955-4720-a0ad-3750e1bc89d0" : {
         "desc" : "メタデータをXML形式でダウンロードします。",
         "file_name" : "eg000019.xml",
         "length" : 3234,
         "mime" : "application/rdf\u002Bxml",
         "sha256" : "0e97359f87167cfd4f8c03356b12ecada0955ad4c04636116feebed874e11d8b",
         "time" : 1733652753,
         "title" : "メタデータ（詳細）",
         "type" : "file",
         "url" : "https://catalog.registries.digital.go.jp/rc/dataset/eg000019.xml"
      },
      "meta:activity.html" : {
         "desc" : "",
         "length" : 19896,
         "mime" : "text/html; charset=utf-8",
         "sha256" : "8e3fa6c1af75672b03abe747b6e7c39dbc5fbaa2c6a4ae5df14ad2587b5ccc71",
         "time" : 1733652747,
         "title" : "",
         "type" : "meta",
         "url" : "https://catalog.registries.digital.go.jp/rc/dataset/activity/eg000019"
      },
      "meta:ckan.json" : {
         "desc" : "",
         "length" : 5456,
         "mime" : "application/json;charset=utf-8",
         "sha256" : "769fedb84bc5620435a792b90ee3fe68cf9a5f3b9e13eca9f4ca05fabda21755",
         "time" : 1727827353.15993,
         "title" : "法令種別/事業",
         "type" : "meta",
         "url" : "https://catalog.registries.digital.go.jp/rc/api/action/package_show?id=eg000019"
      }
   },
   "legal" : {
      "is_free" : "free",
      "legal" : [
         {
            "dir" : "ltr",
            "full_url" : "https://creativecommons.org/licenses/by/4.0/",
            "is_free" : "free",
            "key" : "CC-BY-4.0",
            "label" : "Creative Commons Attribution 4.0 International",
            "lang" : "en",
            "notice" : {
               "holder" : {
                  "dir" : "auto",
                  "lang" : "ja",
                  "value" : "デジタル庁",
                  "writing_mode" : "horizontal-tb"
               },
               "need_modified_flag" : 1,
               "title" : {
                  "dir" : "auto",
                  "lang" : "ja",
                  "value" : "法令種別/事業",
                  "writing_mode" : "horizontal-tb"
               },
               "url" : "https://catalog.registries.digital.go.jp/rc/dataset/eg000019"
            },
            "source_type" : "package",
            "source_url" : "https://catalog.registries.digital.go.jp/rc/api/action/package_show?id=eg000019",
            "type" : "license",
            "writing_mode" : "horizontal-tb"
         },
         {
            "alt" : [
               {
                  "dir" : "ltr",
                  "full_url" : "https://creativecommons.org/licenses/by/4.0/",
                  "is_free" : "free",
                  "key" : "CC-BY-4.0",
                  "label" : "Creative Commons Attribution 4.0 International",
                  "lang" : "en",
                  "notice" : {
                     "holder" : {
                        "dir" : "ltr",
                        "lang" : "ja",
                        "value" : "デジタル庁",
                        "writing_mode" : "horizontal-tb"
                     },
                     "need_modified_flag" : 1,
                     "title" : {
                        "dir" : "auto",
                        "lang" : "ja",
                        "value" : "法令種別/事業",
                        "writing_mode" : "horizontal-tb"
                     },
                     "url" : "https://catalog.registries.digital.go.jp/rc/dataset/eg000019"
                  },
                  "type" : "license",
                  "writing_mode" : "horizontal-tb"
               }
            ],
            "dir" : "ltr",
            "full_url" : "https://catalog.registries.digital.go.jp/rc/terms",
            "is_free" : "unknown",
            "key" : "-ddsd-terms-catalog.registries.digital.go.jp",
            "label" : "利用規約 - レジストリカタログ",
            "lang" : "ja",
            "notice" : {
               "holder" : {
                  "dir" : "ltr",
                  "lang" : "ja",
                  "value" : "デジタル庁",
                  "writing_mode" : "horizontal-tb"
               },
               "need_modified_flag" : 1,
               "template" : {
                  "dir" : "ltr",
                  "lang" : "ja",
                  "value" : "「{title}」（{holder}）（{url}）を加工して作成",
                  "writing_mode" : "horizontal-tb"
               },
               "template_not_modified" : {
                  "dir" : "ltr",
                  "lang" : "ja",
                  "value" : "レジストリカタログ（{url}）",
                  "writing_mode" : "horizontal-tb"
               },
               "title" : {
                  "dir" : "auto",
                  "lang" : "ja",
                  "value" : "法令種別/事業",
                  "writing_mode" : "horizontal-tb"
               },
               "url" : "https://catalog.registries.digital.go.jp/rc/dataset/eg000019"
            },
            "source_type" : "site",
            "source_url" : "https://catalog.registries.digital.go.jp/rc/terms",
            "type" : "site_terms",
            "writing_mode" : "horizontal-tb"
         },
         {
            "dir" : "ltr",
            "is_free" : "neutral",
            "key" : "-ddsd-disclaimer",
            "lang" : "ja",
            "notice" : {
               "template" : {
                  "dir" : "ltr",
                  "lang" : "ja",
                  "value" : "これらの法的な表示はソフトウェアにより機械的に抽出・生成したものです。ソフトウェアの制作者はその正確性、完全性、その他を一切保証しません。",
                  "writing_mode" : "horizontal-tb"
               }
            },
            "source_type" : "sniffer",
            "type" : "disclaimer",
            "writing_mode" : "horizontal-tb"
         }
      ]
   },
   "length" : 293463,
   "mirrorzip" : {
      "length" : 271247,
      "set" : "free-1",
      "sha256" : "7b4b03328b5e5728f8c358bcf202335a56480a0719f7b629229bf06ed16d0f15"
   },
   "package" : {
      "author" : "",
      "ckan_api_url" : "https://catalog.registries.digital.go.jp/rc/api/action/package_show?id=eg000019",
      "desc" : "e-Gov法令検索サイトで公開されている法令種別/事業データセットです。",
      "org" : "デジタル庁",
      "page_url" : "https://catalog.registries.digital.go.jp/rc/dataset/eg000019",
      "tags" : [
         "デジタル庁",
         "法律・制度",
         "勅令",
         "府省令",
         "憲法",
         "政令",
         "法令",
         "法律",
         "規則"
      ],
      "time" : 1727827353.15993,
      "title" : "法令種別/事業"
   }
}
